hello_world/__init__.py
hello_world/main.py
lytepipe-0.0.1.dist-info/LICENSE
lytepipe-0.0.1.dist-info/METADATA
lytepipe-0.0.1.dist-info/WHEEL
lytepipe-0.0.1.dist-info/top_level.txt
lytepipe-0.0.1.dist-info/RECORD
