Metadata-Version: 2.1
Name: lytepipe
Version: 0.0.1
Summary: A Hello World package
Home-page: https://github.com/xxxxx/xxxx
Author: GVas
Author-email: gvas@xxxxxxxxxxxxxx.com
License: UNKNOWN
Platform: UNKNOWN
Classifier: Programming Language :: Python :: 3.8
Classifier: License :: OSI Approved :: MIT License
Classifier: Operating System :: OS Independent
Requires-Python: >=3.6
